jaxgw/__init__.py
jaxgw/PE/__init__.py
jaxgw/PE/constants.py
jaxgw/PE/detector_preset.py
jaxgw/PE/detector_projection.py
jaxgw/PE/generate_noise.py
jaxgw/PE/heterodyneLikelihood.py
jaxgw/PE/single_event_likelihood.py
jaxgw/PE/time_and_date.py
jaxgw/PE/utils.py
jaxGW-0.0.4.2.dist-info/LICENSE
jaxGW-0.0.4.2.dist-info/METADATA
jaxGW-0.0.4.2.dist-info/WHEEL
jaxGW-0.0.4.2.dist-info/top_level.txt
jaxGW-0.0.4.2.dist-info/RECORD
