Metadata-Version: 2.1
Name: jaxGW
Version: 0.0.4.2
Summary: Gravitatioanl wave data analysis tool in Jax
Home-page: https://github.com/kazewong/JaxGW
Author: Kaze Wong
Author-email: kazewong.physics@gmail.com
License: MIT
Keywords: sampling,inference,machine learning,normalizing,autodiff,jax
Requires-Python: >=3.7
License-File: LICENSE
Requires-Dist: jax
Requires-Dist: jaxlib
Requires-Dist: flax
